{
  "generated_at_utc": "2026-04-21T13:54:44.932354+00:00",
  "checkpoint": "/Users/krishpatel/CMU/05318/Art or Algorithm/models/final_vit.pth",
  "validation_dir": "/Users/krishpatel/CMU/05318/Art or Algorithm/data/val",
  "confidence_threshold_wrong_class": 0.7,
  "failure_count": 18,
  "failures": [
    {
      "filename": "000_trueai_predhuman_p0.892_100960167.jpg.jpg",
      "public_url_path": "/failures/000_trueai_predhuman_p0.892_100960167.jpg.jpg",
      "true_label": "ai",
      "predicted_label": "human",
      "confidence_in_predicted_class": 0.892232,
      "probabilities": {
        "ai": 0.10776784271001816,
        "human": 0.8922321796417236
      },
      "why_the_model_may_have_struggled": [
        "Geometry: 720×1280px, aspect ratio 0.56. Laplacian variance ≈ 208.0 (proxy for fine detail / sharpness).",
        "Color spread (mean BGR channel std) ≈ 48.7 — richer palettes can correlate with either photographic captures or heavily stylized AI outputs.",
        "Possible failure story: brushy strokes, noise, or traditional-media mimicry in AI outputs overlap human-art texture statistics the model relied on."
      ]
    },
    {
      "filename": "001_trueai_predhuman_p0.784_8A9FC0D0-D02D-4909-8E7B90874F98DBF2_source.jpg.jpg",
      "public_url_path": "/failures/001_trueai_predhuman_p0.784_8A9FC0D0-D02D-4909-8E7B90874F98DBF2_source.jpg.jpg",
      "true_label": "ai",
      "predicted_label": "human",
      "confidence_in_predicted_class": 0.783907,
      "probabilities": {
        "ai": 0.21609286963939667,
        "human": 0.7839071154594421
      },
      "why_the_model_may_have_struggled": [
        "Geometry: 1536×1331px, aspect ratio 1.15. Laplacian variance ≈ 634.5 (proxy for fine detail / sharpness).",
        "Color spread (mean BGR channel std) ≈ 46.7 — richer palettes can correlate with either photographic captures or heavily stylized AI outputs.",
        "HCI angle: strong micro-texture can look 'physical' or photographic; synthetic images that mimic film grain or canvas can be mislabeled as human.",
        "Possible failure story: brushy strokes, noise, or traditional-media mimicry in AI outputs overlap human-art texture statistics the model relied on."
      ]
    },
    {
      "filename": "002_trueai_predhuman_p0.867_Animals04april2023.jpg.jpg",
      "public_url_path": "/failures/002_trueai_predhuman_p0.867_Animals04april2023.jpg.jpg",
      "true_label": "ai",
      "predicted_label": "human",
      "confidence_in_predicted_class": 0.866992,
      "probabilities": {
        "ai": 0.13300833106040955,
        "human": 0.8669916391372681
      },
      "why_the_model_may_have_struggled": [
        "Geometry: 594×404px, aspect ratio 1.47. Laplacian variance ≈ 2538.9 (proxy for fine detail / sharpness).",
        "Color spread (mean BGR channel std) ≈ 52.4 — richer palettes can correlate with either photographic captures or heavily stylized AI outputs.",
        "HCI angle: strong micro-texture can look 'physical' or photographic; synthetic images that mimic film grain or canvas can be mislabeled as human.",
        "Possible failure story: brushy strokes, noise, or traditional-media mimicry in AI outputs overlap human-art texture statistics the model relied on."
      ]
    },
    {
      "filename": "003_trueai_predhuman_p0.944_Bu69yrI45ueNWQX84ap5.jpg.jpg",
      "public_url_path": "/failures/003_trueai_predhuman_p0.944_Bu69yrI45ueNWQX84ap5.jpg.jpg",
      "true_label": "ai",
      "predicted_label": "human",
      "confidence_in_predicted_class": 0.94403,
      "probabilities": {
        "ai": 0.05597027391195297,
        "human": 0.944029688835144
      },
      "why_the_model_may_have_struggled": [
        "Geometry: 1024×768px, aspect ratio 1.33. Laplacian variance ≈ 351.3 (proxy for fine detail / sharpness).",
        "Color spread (mean BGR channel std) ≈ 63.4 — richer palettes can correlate with either photographic captures or heavily stylized AI outputs.",
        "HCI angle: strong micro-texture can look 'physical' or photographic; synthetic images that mimic film grain or canvas can be mislabeled as human.",
        "Possible failure story: brushy strokes, noise, or traditional-media mimicry in AI outputs overlap human-art texture statistics the model relied on."
      ]
    },
    {
      "filename": "004_trueai_predhuman_p0.819_Dave-McKean-3.jpeg.jpeg",
      "public_url_path": "/failures/004_trueai_predhuman_p0.819_Dave-McKean-3.jpeg.jpeg",
      "true_label": "ai",
      "predicted_label": "human",
      "confidence_in_predicted_class": 0.818999,
      "probabilities": {
        "ai": 0.18100063502788544,
        "human": 0.8189994096755981
      },
      "why_the_model_may_have_struggled": [
        "Geometry: 2048×1536px, aspect ratio 1.33. Laplacian variance ≈ 32.3 (proxy for fine detail / sharpness).",
        "Color spread (mean BGR channel std) ≈ 51.9 — richer palettes can correlate with either photographic captures or heavily stylized AI outputs.",
        "HCI angle: very smooth, low-detail regions are a cue the model often associates with generative art; minimalist human work can be unfairly pulled toward 'AI'.",
        "Possible failure story: brushy strokes, noise, or traditional-media mimicry in AI outputs overlap human-art texture statistics the model relied on."
      ]
    },
    {
      "filename": "005_trueai_predhuman_p0.820_Julian-van-Dieken_A-Girl-With-Glowing-Earrings-.png.png",
      "public_url_path": "/failures/005_trueai_predhuman_p0.820_Julian-van-Dieken_A-Girl-With-Glowing-Earrings-.png.png",
      "true_label": "ai",
      "predicted_label": "human",
      "confidence_in_predicted_class": 0.819978,
      "probabilities": {
        "ai": 0.18002185225486755,
        "human": 0.8199781775474548
      },
      "why_the_model_may_have_struggled": [
        "Geometry: 652×815px, aspect ratio 0.80. Laplacian variance ≈ 132.6 (proxy for fine detail / sharpness).",
        "Color spread (mean BGR channel std) ≈ 57.8 — richer palettes can correlate with either photographic captures or heavily stylized AI outputs.",
        "Possible failure story: brushy strokes, noise, or traditional-media mimicry in AI outputs overlap human-art texture statistics the model relied on."
      ]
    },
    {
      "filename": "006_trueai_predhuman_p0.894_ai-generated-8247695_1280.jpg.jpg",
      "public_url_path": "/failures/006_trueai_predhuman_p0.894_ai-generated-8247695_1280.jpg.jpg",
      "true_label": "ai",
      "predicted_label": "human",
      "confidence_in_predicted_class": 0.894141,
      "probabilities": {
        "ai": 0.10585933923721313,
        "human": 0.8941406607627869
      },
      "why_the_model_may_have_struggled": [
        "Geometry: 853×1280px, aspect ratio 0.67. Laplacian variance ≈ 690.2 (proxy for fine detail / sharpness).",
        "Color spread (mean BGR channel std) ≈ 48.6 — richer palettes can correlate with either photographic captures or heavily stylized AI outputs.",
        "HCI angle: strong micro-texture can look 'physical' or photographic; synthetic images that mimic film grain or canvas can be mislabeled as human.",
        "Possible failure story: brushy strokes, noise, or traditional-media mimicry in AI outputs overlap human-art texture statistics the model relied on."
      ]
    },
    {
      "filename": "007_trueai_predhuman_p0.870_robot-monitoring-dairy-farm-1200x800-1.jpg.jpg",
      "public_url_path": "/failures/007_trueai_predhuman_p0.870_robot-monitoring-dairy-farm-1200x800-1.jpg.jpg",
      "true_label": "ai",
      "predicted_label": "human",
      "confidence_in_predicted_class": 0.870492,
      "probabilities": {
        "ai": 0.1295083910226822,
        "human": 0.8704915642738342
      },
      "why_the_model_may_have_struggled": [
        "Geometry: 1200×800px, aspect ratio 1.50. Laplacian variance ≈ 674.5 (proxy for fine detail / sharpness).",
        "Color spread (mean BGR channel std) ≈ 72.9 — richer palettes can correlate with either photographic captures or heavily stylized AI outputs.",
        "HCI angle: strong micro-texture can look 'physical' or photographic; synthetic images that mimic film grain or canvas can be mislabeled as human.",
        "Possible failure story: brushy strokes, noise, or traditional-media mimicry in AI outputs overlap human-art texture statistics the model relied on."
      ]
    },
    {
      "filename": "008_truehuman_predai_p0.970_172711.jpg.jpg",
      "public_url_path": "/failures/008_truehuman_predai_p0.970_172711.jpg.jpg",
      "true_label": "human",
      "predicted_label": "ai",
      "confidence_in_predicted_class": 0.970257,
      "probabilities": {
        "ai": 0.970256507396698,
        "human": 0.029743487015366554
      },
      "why_the_model_may_have_struggled": [
        "Geometry: 867×1300px, aspect ratio 0.67. Laplacian variance ≈ 5086.7 (proxy for fine detail / sharpness).",
        "Color spread (mean BGR channel std) ≈ 75.0 — richer palettes can correlate with either photographic captures or heavily stylized AI outputs.",
        "HCI angle: strong micro-texture can look 'physical' or photographic; synthetic images that mimic film grain or canvas can be mislabeled as human.",
        "Possible failure story: clean vector-like composition, flat shading, or digital poster aesthetics overlap the training distribution of AI samples."
      ]
    },
    {
      "filename": "009_truehuman_predai_p0.917_Fschl-Eric_TrumpMug.jpg.jpg",
      "public_url_path": "/failures/009_truehuman_predai_p0.917_Fschl-Eric_TrumpMug.jpg.jpg",
      "true_label": "human",
      "predicted_label": "ai",
      "confidence_in_predicted_class": 0.916673,
      "probabilities": {
        "ai": 0.9166730642318726,
        "human": 0.08332695811986923
      },
      "why_the_model_may_have_struggled": [
        "Geometry: 1280×960px, aspect ratio 1.33. Laplacian variance ≈ 427.2 (proxy for fine detail / sharpness).",
        "Color spread (mean BGR channel std) ≈ 59.8 — richer palettes can correlate with either photographic captures or heavily stylized AI outputs.",
        "HCI angle: strong micro-texture can look 'physical' or photographic; synthetic images that mimic film grain or canvas can be mislabeled as human.",
        "Possible failure story: clean vector-like composition, flat shading, or digital poster aesthetics overlap the training distribution of AI samples."
      ]
    },
    {
      "filename": "010_truehuman_predai_p0.760_PaintingBBR147_1.jpg.jpg",
      "public_url_path": "/failures/010_truehuman_predai_p0.760_PaintingBBR147_1.jpg.jpg",
      "true_label": "human",
      "predicted_label": "ai",
      "confidence_in_predicted_class": 0.760441,
      "probabilities": {
        "ai": 0.7604409456253052,
        "human": 0.2395591139793396
      },
      "why_the_model_may_have_struggled": [
        "Geometry: 1500×1500px, aspect ratio 1.00. Laplacian variance ≈ 594.8 (proxy for fine detail / sharpness).",
        "Color spread (mean BGR channel std) ≈ 71.1 — richer palettes can correlate with either photographic captures or heavily stylized AI outputs.",
        "HCI angle: strong micro-texture can look 'physical' or photographic; synthetic images that mimic film grain or canvas can be mislabeled as human.",
        "Possible failure story: clean vector-like composition, flat shading, or digital poster aesthetics overlap the training distribution of AI samples."
      ]
    },
    {
      "filename": "011_truehuman_predai_p0.820_Shelley-Newman-Watching-The-Show-2022.jpg.jpg",
      "public_url_path": "/failures/011_truehuman_predai_p0.820_Shelley-Newman-Watching-The-Show-2022.jpg.jpg",
      "true_label": "human",
      "predicted_label": "ai",
      "confidence_in_predicted_class": 0.819549,
      "probabilities": {
        "ai": 0.8195488452911377,
        "human": 0.1804511398077011
      },
      "why_the_model_may_have_struggled": [
        "Geometry: 742×745px, aspect ratio 1.00. Laplacian variance ≈ 2931.5 (proxy for fine detail / sharpness).",
        "Color spread (mean BGR channel std) ≈ 62.4 — richer palettes can correlate with either photographic captures or heavily stylized AI outputs.",
        "HCI angle: strong micro-texture can look 'physical' or photographic; synthetic images that mimic film grain or canvas can be mislabeled as human.",
        "Possible failure story: clean vector-like composition, flat shading, or digital poster aesthetics overlap the training distribution of AI samples."
      ]
    },
    {
      "filename": "012_truehuman_predai_p0.725_beautiful-nature-scenery-smartphone-wallpaper-free-photo.jpg.jpg",
      "public_url_path": "/failures/012_truehuman_predai_p0.725_beautiful-nature-scenery-smartphone-wallpaper-free-photo.jpg.jpg",
      "true_label": "human",
      "predicted_label": "ai",
      "confidence_in_predicted_class": 0.725481,
      "probabilities": {
        "ai": 0.7254805564880371,
        "human": 0.27451950311660767
      },
      "why_the_model_may_have_struggled": [
        "Geometry: 3264×5824px, aspect ratio 0.56. Laplacian variance ≈ 889.8 (proxy for fine detail / sharpness).",
        "Color spread (mean BGR channel std) ≈ 66.9 — richer palettes can correlate with either photographic captures or heavily stylized AI outputs.",
        "HCI angle: strong micro-texture can look 'physical' or photographic; synthetic images that mimic film grain or canvas can be mislabeled as human.",
        "Possible failure story: clean vector-like composition, flat shading, or digital poster aesthetics overlap the training distribution of AI samples."
      ]
    },
    {
      "filename": "013_truehuman_predai_p0.749_cat-with-ducklings.jpg.jpg",
      "public_url_path": "/failures/013_truehuman_predai_p0.749_cat-with-ducklings.jpg.jpg",
      "true_label": "human",
      "predicted_label": "ai",
      "confidence_in_predicted_class": 0.749204,
      "probabilities": {
        "ai": 0.7492038011550903,
        "human": 0.25079622864723206
      },
      "why_the_model_may_have_struggled": [
        "Geometry: 1080×720px, aspect ratio 1.50. Laplacian variance ≈ 929.5 (proxy for fine detail / sharpness).",
        "Color spread (mean BGR channel std) ≈ 67.2 — richer palettes can correlate with either photographic captures or heavily stylized AI outputs.",
        "HCI angle: strong micro-texture can look 'physical' or photographic; synthetic images that mimic film grain or canvas can be mislabeled as human.",
        "Possible failure story: clean vector-like composition, flat shading, or digital poster aesthetics overlap the training distribution of AI samples."
      ]
    },
    {
      "filename": "014_truehuman_predai_p0.811_ef2646b821cca54a5ad1cdfcf95d2a1a.jpg.jpg",
      "public_url_path": "/failures/014_truehuman_predai_p0.811_ef2646b821cca54a5ad1cdfcf95d2a1a.jpg.jpg",
      "true_label": "human",
      "predicted_label": "ai",
      "confidence_in_predicted_class": 0.811378,
      "probabilities": {
        "ai": 0.8113778233528137,
        "human": 0.18862216174602509
      },
      "why_the_model_may_have_struggled": [
        "Geometry: 681×960px, aspect ratio 0.71. Laplacian variance ≈ 189.2 (proxy for fine detail / sharpness).",
        "Color spread (mean BGR channel std) ≈ 56.0 — richer palettes can correlate with either photographic captures or heavily stylized AI outputs.",
        "Possible failure story: clean vector-like composition, flat shading, or digital poster aesthetics overlap the training distribution of AI samples."
      ]
    },
    {
      "filename": "015_truehuman_predai_p0.855_female-face-girl-with-wind-in-hair.jpg.jpg",
      "public_url_path": "/failures/015_truehuman_predai_p0.855_female-face-girl-with-wind-in-hair.jpg.jpg",
      "true_label": "human",
      "predicted_label": "ai",
      "confidence_in_predicted_class": 0.855087,
      "probabilities": {
        "ai": 0.8550868630409241,
        "human": 0.14491315186023712
      },
      "why_the_model_may_have_struggled": [
        "Geometry: 467×700px, aspect ratio 0.67. Laplacian variance ≈ 310.4 (proxy for fine detail / sharpness).",
        "Color spread (mean BGR channel std) ≈ 40.2 — richer palettes can correlate with either photographic captures or heavily stylized AI outputs.",
        "HCI angle: strong micro-texture can look 'physical' or photographic; synthetic images that mimic film grain or canvas can be mislabeled as human.",
        "Possible failure story: clean vector-like composition, flat shading, or digital poster aesthetics overlap the training distribution of AI samples."
      ]
    },
    {
      "filename": "016_truehuman_predai_p0.926_homeless-man-color-poverty.jpg.jpg",
      "public_url_path": "/failures/016_truehuman_predai_p0.926_homeless-man-color-poverty.jpg.jpg",
      "true_label": "human",
      "predicted_label": "ai",
      "confidence_in_predicted_class": 0.926261,
      "probabilities": {
        "ai": 0.9262609481811523,
        "human": 0.07373903691768646
      },
      "why_the_model_may_have_struggled": [
        "Geometry: 4000×5000px, aspect ratio 0.80. Laplacian variance ≈ 1606.8 (proxy for fine detail / sharpness).",
        "Color spread (mean BGR channel std) ≈ 61.9 — richer palettes can correlate with either photographic captures or heavily stylized AI outputs.",
        "HCI angle: strong micro-texture can look 'physical' or photographic; synthetic images that mimic film grain or canvas can be mislabeled as human.",
        "Possible failure story: clean vector-like composition, flat shading, or digital poster aesthetics overlap the training distribution of AI samples."
      ]
    },
    {
      "filename": "017_truehuman_predai_p0.762_wers-blooming-green-grass-spring-concept-generative-ai-technology-free-p.jpg",
      "public_url_path": "/failures/017_truehuman_predai_p0.762_wers-blooming-green-grass-spring-concept-generative-ai-technology-free-p.jpg",
      "true_label": "human",
      "predicted_label": "ai",
      "confidence_in_predicted_class": 0.762303,
      "probabilities": {
        "ai": 0.762302815914154,
        "human": 0.23769716918468475
      },
      "why_the_model_may_have_struggled": [
        "Geometry: 347×200px, aspect ratio 1.74. Laplacian variance ≈ 1526.1 (proxy for fine detail / sharpness).",
        "Color spread (mean BGR channel std) ≈ 62.1 — richer palettes can correlate with either photographic captures or heavily stylized AI outputs.",
        "HCI angle: strong micro-texture can look 'physical' or photographic; synthetic images that mimic film grain or canvas can be mislabeled as human.",
        "Possible failure story: clean vector-like composition, flat shading, or digital poster aesthetics overlap the training distribution of AI samples."
      ]
    }
  ]
}